README.md
setup.py
symigrate/__init__.py
symigrate/commandline_parser_creator.py
symigrate/defaults.py
symigrate/migration.py
symigrate/migration_execution_result.py
symigrate/migration_file_matcher.py
symigrate/migration_merge_service.py
symigrate/migration_script_checker.py
symigrate/migration_script_runner.py
symigrate/migration_status.py
symigrate.egg-info/PKG-INFO
symigrate.egg-info/SOURCES.txt
symigrate.egg-info/dependency_links.txt
symigrate.egg-info/entry_points.txt
symigrate.egg-info/requires.txt
symigrate.egg-info/top_level.txt
symigrate/command/__init__.py
symigrate/command/diff_command.py
symigrate/command/info_command.py
symigrate/command/migrate_command.py
symigrate/main/__init__.py
symigrate/main/symigrate.py
symigrate/repository/__init__.py
symigrate/repository/executed_migration_repository.py
symigrate/repository/executed_migration_repository_statements.py
symigrate/repository/migration_script_repository.py
test/__init__.py
test/symigrate/__init__.py
test/symigrate/commandline_parser_creator_test.py
test/symigrate/executed_migration_repository_test.py
test/symigrate/helper.py
test/symigrate/migration_file_matcher_test.py
test/symigrate/migration_merge_service_test.py
test/symigrate/migration_script_repository_integration_test.py
test/symigrate/acceptance_test/__init__.py
test/symigrate/acceptance_test/diff_command_acceptance_test.py
test/symigrate/acceptance_test/global_commands_acceptance_test.py
test/symigrate/acceptance_test/info_command_acceptance_test.py
test/symigrate/acceptance_test/migrate_command_acceptance_test.py