Metadata-Version: 1.1
Name: symigrate
Version: 0.1.1
Summary: A flyway-like tool that allows migration of scripts to a system.
Home-page: UNKNOWN
Author: Erik Tuerke
Author-email: etuerke@googlemail.com
License: Apache2
Platform: UNKNOWN
Classifier: Intended Audience :: System Administrators
Classifier: Programming Language :: Python :: 3 :: Only
Classifier: Development Status :: 2 - Pre-Alpha
Classifier: Environment :: Console
